Metadata-Version: 2.1
Name: odoo10-addon-account-set-reconcilable
Version: 10.0.1.0.0
Summary: Allows to set as reconcilable a non reconcilableaccount that already have journal items.
Home-page: http://www.github.com/OCA/account-reconcile
Author: Eficent, Odoo Community Association (OCA)
Author-email: support@odoo-community.org
License: AGPL-3
Platform: UNKNOWN
Classifier: Programming Language :: Python
Classifier: Framework :: Odoo
Classifier: License :: OSI Approved :: GNU Affero General Public License v3
Requires-Python: ~=2.7
Requires-Dist: odoo (<10.1dev,>=10.0)
